tiscope/__init__.py
tiscope/function.py
tiscope/layer.py
tiscope/model.py
tiscope/utils.py
tiscope-0.0.2.dist-info/licenses/LICENSE
tiscope-0.0.2.dist-info/METADATA
tiscope-0.0.2.dist-info/WHEEL
tiscope-0.0.2.dist-info/top_level.txt
tiscope-0.0.2.dist-info/RECORD
