Metadata-Version: 2.4
Name: tiscope
Version: 0.0.2
Summary: TISCOPE
Author-email: Yuzhe Li <liyuzhezju@gmail.com>, Weixi Ning <aaronning98@gmail.com>
License: MIT
Project-URL: Homepage, https://github.com/zhangqf-lab/TISCOPE
Project-URL: Bug Tracker, https://github.com/zhangqf-lab/TISCOPE/issues
Classifier: Programming Language :: Python :: 3
Classifier: Operating System :: OS Independent
Classifier: Development Status :: 4 - Beta
Classifier: Intended Audience :: Science/Research
Classifier: Topic :: Scientific/Engineering :: Bio-Informatics
Requires-Python: >=3.10
License-File: LICENSE
Requires-Dist: numpy
Requires-Dist: pandas
Requires-Dist: scipy
Requires-Dist: scikit-learn
Requires-Dist: scanpy
Requires-Dist: matplotlib
Requires-Dist: seaborn
Requires-Dist: squidpy
Requires-Dist: bbknn
Dynamic: license-file
